setup_client.py
mess_client_first.egg-info/PKG-INFO
mess_client_first.egg-info/SOURCES.txt
mess_client_first.egg-info/dependency_links.txt
mess_client_first.egg-info/requires.txt
mess_client_first.egg-info/top_level.txt