Metadata-Version: 2.1
Name: mess-client-first
Version: 0.1
Summary: mess_client
Home-page: UNKNOWN
Author: Tatiana Kudryavtseva
Author-email: lexta@list.ru
License: UNKNOWN
Platform: UNKNOWN
